positionalonly/.__init__.py.swp
positionalonly/.__init__.py.un~
positionalonly/__init__.py
positionalonly-0.0.3.dist-info/WHEEL
positionalonly-0.0.3.dist-info/METADATA
positionalonly-0.0.3.dist-info/RECORD
