Metadata-Version: 1.2
Name: positionalonly
Version: 0.0.3
Summary: positionnal only arguments/parameters
Home-page: https://github.com/Carreau/positionalonly
License: UNKNOWN
Author: Matthias Bussonnier
Author-email: bussonniermatthias@gmail.com
Requires-Python: >=3.5
Classifier: License :: OSI Approved :: MIT License
